pytest_xhtml/__init__.py
pytest_xhtml/__version.py
pytest_xhtml/basereport.py
pytest_xhtml/extras.py
pytest_xhtml/fixtures.py
pytest_xhtml/hooks.py
pytest_xhtml/plugin.py
pytest_xhtml/report.py
pytest_xhtml/report_data.py
pytest_xhtml/selfcontained_report.py
pytest_xhtml/util.py
pytest_xhtml/resources/app.js
pytest_xhtml/resources/index.jinja2
pytest_xhtml/resources/style.css
pytest_xhtml-0.3.0.dist-info/METADATA
pytest_xhtml-0.3.0.dist-info/WHEEL
pytest_xhtml-0.3.0.dist-info/entry_points.txt
pytest_xhtml-0.3.0.dist-info/licenses/LICENSE
pytest_xhtml-0.3.0.dist-info/RECORD
